README.md
setup.py
qfracture/__init__.py
qfracture/browser.py
qfracture/constants.py
qfracture/core.py
qfracture/menus.py
qfracture/run.py
qfracture/wizard.py
qfracture.egg-info/PKG-INFO
qfracture.egg-info/SOURCES.txt
qfracture.egg-info/dependency_links.txt
qfracture.egg-info/requires.txt
qfracture.egg-info/top_level.txt
qfracture/_res/Add to Favourites.png
qfracture/_res/Copy Path.png
qfracture/_res/Remove from Favourites.png
qfracture/_res/above.png
qfracture/_res/below.png
qfracture/_res/current.png
qfracture/_res/fracture.png
qfracture/_res/fracture.ui
qfracture/_res/qfracture.css
qfracture/_res/search.png
qfracture/_res/wizard.png
qfracture/_res/wizard_page_one.ui
qfracture/_res/wizard_page_three.ui
qfracture/_res/wizard_page_two.ui
qfracture/delegates/default.py
qfracture/tray/__init__.py
qfracture/tray/core.py