Metadata-Version: 2.1
Name: qfracture
Version: 0.9.2
Summary: qFracture is a lightweight UI atop of fracture
Home-page: https://github.com/mikemalinowski/qfracture
Author: Mike Malinowski
Author-email: mike@twisted.space
License: UNKNOWN
Keywords: fracture data composite qfracture
Platform: UNKNOWN
Classifier: Programming Language :: Python
Classifier: License :: OSI Approved :: MIT License
Classifier: Operating System :: OS Independent
